dockerpty/__init__.py
dockerpty/io.py
dockerpty/pty.py
dockerpty/tty.py
envy_project_dockerpty_republish-999.4.2.dist-info/LICENSE.txt
envy_project_dockerpty_republish-999.4.2.dist-info/METADATA
envy_project_dockerpty_republish-999.4.2.dist-info/WHEEL
envy_project_dockerpty_republish-999.4.2.dist-info/top_level.txt
envy_project_dockerpty_republish-999.4.2.dist-info/RECORD
